Metadata-Version: 2.4
Name: freecad-mcp-fastmcp
Version: 0.1.14
Summary: Add your description here
Project-URL: Homepage, https://github.com/fastmcp-me/freecad-mcp#readme
Project-URL: Repository, https://github.com/fastmcp-me/freecad-mcp.git
Project-URL: Issues, https://github.com/fastmcp-me/freecad-mcp/issues
Author-email: neka-nat <nekanat.stock@gmail.com>
License: MIT
License-File: LICENSE
Requires-Python: >=3.12
Requires-Dist: mcp[cli]>=1.12.2
